{
  "id": "quralan_eclipse_del_killay",
  "name": "Eclipse del K'illay",
  "race": "quralan",
  "type": "event",
  "cost": 3,
  "rarity": "rare",
  "keywords": [],
  "abilities": [
    {
      "trigger": { "kind": "on_play" },
      "category": "initiative",
      "effect": {
        "op": "for_each",
        "filter": { "controller": "opponent", "keywordsAny": ["ignicion"] },
        "effect": {
          "op": "damage",
          "target": { "kind": "self" },
          "amount": 2
        }
      },
      "description": "Al jugarse: hace 2 daño a cada nave enemiga que tenga la keyword ignición."
    }
  ],
  "flavorText": "Cuando el K'illay eclipsa al Sol Quinto, las brasas Tezhal se apagan antes de cantar.",
  "intentionalOffCategory": true
}
